Metadata-Version: 2.1
Name: parserz
Version: 0.15
Summary: Easy parser for parse template $variable
Home-page: https://github.com/hanzhichao/parserz
Author: Han Zhichao
Author-email: superhin@126.com
License: MIT license
Keywords: parserz,parser,dollar parser
Platform: UNKNOWN
Classifier: Programming Language :: Python
Classifier: Programming Language :: Python :: 2.7
Classifier: Programming Language :: Python :: 3.7
